keyed/__init__.py
keyed/animation.py
keyed/annotations.py
keyed/base.py
keyed/cli.py
keyed/color.py
keyed/config.py
keyed/constants.py
keyed/context.py
keyed/curve.py
keyed/debug.py
keyed/easing.py
keyed/effects.py
keyed/extras.py
keyed/geometry.py
keyed/group.py
keyed/helpers.py
keyed/highlight.py
keyed/line.py
keyed/parser.py
keyed/plot.py
keyed/py.typed
keyed/renderer.py
keyed/scene.py
keyed/shapes.py
keyed/text.py
keyed/transforms.py
keyed/types.py
keyed/compositor/__init__.py
keyed/compositor/blend.py
keyed/compositor/compositor_cairo.py
keyed/compositor/compositor_taichi.py
keyed/compositor/core.py
keyed/previewer/__init__.py
keyed/previewer/filewatch.py
keyed/previewer/impl.py
keyed-0.1.2.dist-info/licenses/LICENSE
keyed-0.1.2.dist-info/METADATA
keyed-0.1.2.dist-info/WHEEL
keyed-0.1.2.dist-info/entry_points.txt
keyed-0.1.2.dist-info/top_level.txt
keyed-0.1.2.dist-info/RECORD
