Metadata-Version: 2.4
Name: keyed
Version: 0.1.2
Summary: A reactive animation library.
Author-email: Doug Mercer <dougmerceryt@gmail.com>
License: BSD 3-Clause License
Keywords: keyed,animation,reactive
Classifier: Development Status :: 4 - Beta
Classifier: Intended Audience :: Developers
Classifier: Programming Language :: Python :: 3.11
Classifier: Programming Language :: Python :: 3.12
Requires-Python: <3.13,>=3.11
License-File: LICENSE
Requires-Dist: av
Requires-Dist: pillow
Requires-Dist: pycairo
Requires-Dist: pydantic
Requires-Dist: pygments
Requires-Dist: rich
Requires-Dist: scipy
Requires-Dist: shapely
Requires-Dist: signified
Requires-Dist: tqdm
Requires-Dist: typer
Provides-Extra: lint
Requires-Dist: ruff; extra == "lint"
Requires-Dist: pyright; extra == "lint"
Provides-Extra: test
Requires-Dist: hypothesis; extra == "test"
Requires-Dist: pytest; extra == "test"
Requires-Dist: pytest-cov; extra == "test"
Requires-Dist: syrupy; extra == "test"
Provides-Extra: docs
Requires-Dist: beautifulsoup4; extra == "docs"
Requires-Dist: mkdocs; extra == "docs"
Requires-Dist: mkdocs-material; extra == "docs"
Requires-Dist: mkdocstrings[python]; extra == "docs"
Requires-Dist: mkdocs-material-extensions; extra == "docs"
Provides-Extra: previewer
Requires-Dist: pyside6; extra == "previewer"
Requires-Dist: watchdog; extra == "previewer"
Provides-Extra: gpu-compositor
Requires-Dist: taichi; extra == "gpu-compositor"
Provides-Extra: all
Requires-Dist: keyed[docs,gpu-compositor,lint,previewer,test]; extra == "all"
Dynamic: license-file
